bin/__init__.py
bin/__main__.py
bin/main.py
bin/maven_artifact.py
bin/request.py
maven_artifact_downloader-0.2.6.dist-info/LICENSE
maven_artifact_downloader-0.2.6.dist-info/METADATA
maven_artifact_downloader-0.2.6.dist-info/WHEEL
maven_artifact_downloader-0.2.6.dist-info/entry_points.txt
maven_artifact_downloader-0.2.6.dist-info/top_level.txt
maven_artifact_downloader-0.2.6.dist-info/RECORD
