Metadata-Version: 2.1
Name: maven-artifact-downloader
Version: 0.2.6
Summary: Resolve and download maven artifacts
Home-page: https://git.linecorp.com/filipe-guerreiro/main-downloader
Author: Filipe Guerreiro
Author-email: filipe.guerreiro@linecorp.com
License: GNU 3.0
Keywords: packages
Platform: UNKNOWN
Classifier: Development Status :: 3 - Alpha
Classifier: Intended Audience :: Developers
Classifier: Topic :: Software Development :: Build Tools
Classifier: License :: OSI Approved :: GNU General Public License v3 or later (GPLv3+)
Classifier: Programming Language :: Python :: 2
Classifier: Programming Language :: Python :: 3
Requires-Dist: lxml
Provides-Extra: dev
Requires-Dist: check-manifest ; extra == 'dev'
Provides-Extra: test
Requires-Dist: coverage ; extra == 'test'
